cv2_stack_images/LICENSE
cv2_stack_images/README.MD
cv2_stack_images/__init__.py
cv2_stack_images/requirements.txt
cv2_stack_images/thirdparty.json
cv2_stack_images-0.10.dist-info/LICENSE.rst
cv2_stack_images-0.10.dist-info/METADATA
cv2_stack_images-0.10.dist-info/WHEEL
cv2_stack_images-0.10.dist-info/top_level.txt
cv2_stack_images-0.10.dist-info/RECORD
